oslo_upgradecheck/__init__.py
oslo_upgradecheck/_i18n.py
oslo_upgradecheck/common_checks.py
oslo_upgradecheck/py.typed
oslo_upgradecheck/upgradecheck.py
oslo_upgradecheck/tests/__init__.py
oslo_upgradecheck/tests/test_common_checks.py
oslo_upgradecheck/tests/test_upgradecheck.py
oslo_upgradecheck-2.7.0.dist-info/licenses/AUTHORS
oslo_upgradecheck-2.7.0.dist-info/licenses/LICENSE
oslo_upgradecheck-2.7.0.dist-info/METADATA
oslo_upgradecheck-2.7.0.dist-info/WHEEL
oslo_upgradecheck-2.7.0.dist-info/pbr.json
oslo_upgradecheck-2.7.0.dist-info/top_level.txt
oslo_upgradecheck-2.7.0.dist-info/RECORD
