Metadata-Version: 2.4
Name: oslo.upgradecheck
Version: 2.7.0
Summary: Common code for writing OpenStack upgrade checks
Author-email: OpenStack <openstack-discuss@lists.openstack.org>
License: Apache-2.0
Project-URL: Homepage, https://docs.openstack.org/oslo.upgradecheck
Project-URL: Repository, https://opendev.org/openstack/oslo.upgradecheck
Classifier: Environment :: OpenStack
Classifier: Intended Audience :: Information Technology
Classifier: Intended Audience :: System Administrators
Classifier: License :: OSI Approved :: Apache Software License
Classifier: Operating System :: POSIX :: Linux
Classifier: Programming Language :: Python
Classifier: Programming Language :: Python :: 3
Classifier: Programming Language :: Python :: 3.10
Classifier: Programming Language :: Python :: 3.11
Classifier: Programming Language :: Python :: 3.12
Classifier: Programming Language :: Python :: 3.13
Requires-Python: >=3.10
License-File: LICENSE
License-File: AUTHORS
Requires-Dist: oslo.config>=5.2.0
Requires-Dist: oslo.i18n>=3.15.3
Requires-Dist: PrettyTable>=0.7.1
Requires-Dist: oslo.utils>=4.5.0
Requires-Dist: oslo.policy>=2.0.0
Dynamic: license-file
Dynamic: requires-dist
